gatktool/__init__.py
gatktool/_version.py
gatktool/tool.py
gatktool/toolconstants.py
gcnvkernel/__init__.py
gcnvkernel/_version.py
gcnvkernel/config.py
gcnvkernel/types.py
gcnvkernel/inference/__init__.py
gcnvkernel/inference/convergence_tracker.py
gcnvkernel/inference/deterministic_annealing.py
gcnvkernel/inference/fancy_optimizers.py
gcnvkernel/inference/param_tracker.py
gcnvkernel/io/__init__.py
gcnvkernel/io/io_adamax.py
gcnvkernel/io/io_commons.py
gcnvkernel/io/io_consts.py
gcnvkernel/io/io_denoising_calling.py
gcnvkernel/io/io_intervals_and_counts.py
gcnvkernel/io/io_metadata.py
gcnvkernel/io/io_ploidy.py
gcnvkernel/io/io_vcf_parsing.py
gcnvkernel/io/test_io_vcf_parsing.py
gcnvkernel/models/__init__.py
gcnvkernel/models/commons.py
gcnvkernel/models/dists.py
gcnvkernel/models/fancy_model.py
gcnvkernel/models/model_denoising_calling.py
gcnvkernel/models/model_ploidy.py
gcnvkernel/models/theano_hmm.py
gcnvkernel/postprocess/__init__.py
gcnvkernel/postprocess/segment_quality_utils.py
gcnvkernel/postprocess/test_viterbiSegmentationEngine.py
gcnvkernel/postprocess/viterbi_segmentation.py
gcnvkernel/preprocess/__init__.py
gcnvkernel/preprocess/interval_list_mask.py
gcnvkernel/structs/__init__.py
gcnvkernel/structs/interval.py
gcnvkernel/structs/metadata.py
gcnvkernel/structs/segment.py
gcnvkernel/tasks/__init__.py
gcnvkernel/tasks/inference_task_base.py
gcnvkernel/tasks/task_case_denoising_calling.py
gcnvkernel/tasks/task_case_ploidy_determination.py
gcnvkernel/tasks/task_cohort_denoising_calling.py
gcnvkernel/tasks/task_cohort_ploidy_determination.py
gcnvkernel/utils/__init__.py
gcnvkernel/utils/cli_commons.py
gcnvkernel/utils/math.py
gcnvkernel/utils/rls.py
vqsr_cnn/__init__.py
vqsr_cnn/_version.py
vqsr_cnn/vqsr_cnn/__init__.py
vqsr_cnn/vqsr_cnn/arguments.py
vqsr_cnn/vqsr_cnn/defines.py
vqsr_cnn/vqsr_cnn/inference.py
vqsr_cnn/vqsr_cnn/models.py
vqsr_cnn/vqsr_cnn/plots.py
vqsr_cnn/vqsr_cnn/tensor_maps.py
gatkpythonpackages-0.1.dist-info/METADATA
gatkpythonpackages-0.1.dist-info/WHEEL
gatkpythonpackages-0.1.dist-info/top_level.txt
gatkpythonpackages-0.1.dist-info/RECORD
