Metadata-Version: 2.1
Name: gatkpythonpackages
Version: 0.1
Summary: GATK python packages
Author: GATK Team
